{
  "$schema": "https://ui.shadcn.com/schema/registry-item.json",
  "name": "section-cards",
  "type": "registry:component",
  "title": "Section Cards",
  "description": "Card components for dashboard sections.",
  "files": [
    {
      "path": "registry/new-york/section-cards/section-cards.tsx",
      "content": "import { IconTrendingDown, IconTrendingUp } from \"@tabler/icons-react\"\r\n\r\nimport { Badge } from \"@/components/ui/badge\"\r\nimport {\r\n  Card,\r\n  CardAction,\r\n  CardDescription,\r\n  CardFooter,\r\n  CardHeader,\r\n  CardTitle,\r\n} from \"@/components/ui/card\"\r\n\r\nexport function SectionCards() {\r\n  return (\r\n    <div className=\"grid grid-cols-1 gap-4 px-4 lg:px-6 md:grid-cols-2 lg:grid-cols-4\">\r\n      <Card>\r\n        <CardHeader>\r\n          <CardDescription>Total Revenue</CardDescription>\r\n          <CardTitle className=\"text-2xl font-semibold tabular-nums\">\r\n            $1,250.00\r\n          </CardTitle>\r\n          <CardAction>\r\n            <Badge variant=\"outline\">\r\n              <IconTrendingUp />\r\n              +12.5%\r\n            </Badge>\r\n          </CardAction>\r\n        </CardHeader>\r\n        <CardFooter className=\"flex-col items-start gap-1.5 text-sm\">\r\n          <div className=\"flex gap-2 font-medium\">\r\n            Trending up this month <IconTrendingUp className=\"size-4\" />\r\n          </div>\r\n          <div className=\"text-muted-foreground\">\r\n            Visitors for the last 6 months\r\n          </div>\r\n        </CardFooter>\r\n      </Card>\r\n      <Card>\r\n        <CardHeader>\r\n          <CardDescription>New Customers</CardDescription>\r\n          <CardTitle className=\"text-2xl font-semibold tabular-nums\">\r\n            1,234\r\n          </CardTitle>\r\n          <CardAction>\r\n            <Badge variant=\"outline\">\r\n              <IconTrendingDown />\r\n              -20%\r\n            </Badge>\r\n          </CardAction>\r\n        </CardHeader>\r\n        <CardFooter className=\"flex-col items-start gap-1.5 text-sm\">\r\n          <div className=\"flex gap-2 font-medium\">\r\n            Down 20% this period <IconTrendingDown className=\"size-4\" />\r\n          </div>\r\n          <div className=\"text-muted-foreground\">\r\n            Acquisition needs attention\r\n          </div>\r\n        </CardFooter>\r\n      </Card>\r\n      <Card>\r\n        <CardHeader>\r\n          <CardDescription>Active Accounts</CardDescription>\r\n          <CardTitle className=\"text-2xl font-semibold tabular-nums\">\r\n            45,678\r\n          </CardTitle>\r\n          <CardAction>\r\n            <Badge variant=\"outline\">\r\n              <IconTrendingUp />\r\n              +12.5%\r\n            </Badge>\r\n          </CardAction>\r\n        </CardHeader>\r\n        <CardFooter className=\"flex-col items-start gap-1.5 text-sm\">\r\n          <div className=\"flex gap-2 font-medium\">\r\n            Strong user retention <IconTrendingUp className=\"size-4\" />\r\n          </div>\r\n          <div className=\"text-muted-foreground\">Engagement exceed targets</div>\r\n        </CardFooter>\r\n      </Card>\r\n      <Card>\r\n        <CardHeader>\r\n          <CardDescription>Growth Rate</CardDescription>\r\n          <CardTitle className=\"text-2xl font-semibold tabular-nums\">\r\n            4.5%\r\n          </CardTitle>\r\n          <CardAction>\r\n            <Badge variant=\"outline\">\r\n              <IconTrendingUp />\r\n              +4.5%\r\n            </Badge>\r\n          </CardAction>\r\n        </CardHeader>\r\n        <CardFooter className=\"flex-col items-start gap-1.5 text-sm\">\r\n          <div className=\"flex gap-2 font-medium\">\r\n            Steady performance increase <IconTrendingUp className=\"size-4\" />\r\n          </div>\r\n          <div className=\"text-muted-foreground\">Meets growth projections</div>\r\n        </CardFooter>\r\n      </Card>\r\n    </div>\r\n  )\r\n} ",
      "type": "registry:component"
    }
  ]
}